django_backup_migrations/__init__.py
django_backup_migrations/apps.py
django_backup_migrations/core/__init__.py
django_backup_migrations/core/domain/__init__.py
django_backup_migrations/core/domain/model.py
django_backup_migrations/core/strategies/__init__.py
django_backup_migrations/core/strategies/dbtable.py
django_backup_migrations/management/__init__.py
django_backup_migrations/management/commands/__init__.py
django_backup_migrations/management/commands/backupmigrate.py
django_backup_migrations/tests/__init__.py
django_backup_migrations-1.0.0.dist-info/METADATA
django_backup_migrations-1.0.0.dist-info/WHEEL
django_backup_migrations-1.0.0.dist-info/top_level.txt
django_backup_migrations-1.0.0.dist-info/RECORD
